{"trial_id": "cd4f25ddad1020292bb58d9144f40db8", "hyperparameters": {"space": [{"class_name": "Float", "config": {"name": "bias", "default": -100.0, "min_value": -100.0, "max_value": 100.0, "step": null, "sampling": null}}], "values": {"bias": -40.808434937958914}}, "metrics": {"metrics": {"loss": {"direction": "min", "observations": [{"value": [1665.328369140625], "step": 0}]}, "output": {"direction": "min", "observations": [{"value": [1.0], "step": 0}]}}}, "score": 1.0, "best_step": 0, "status": "COMPLETED"}